pywgraph/__init__.py
pywgraph/_wrappers.py
pywgraph/exceptions/__init__.py
pywgraph/exceptions/_exceptions.py
pywgraph/graphs/__init__.py
pywgraph/graphs/_edge.py
pywgraph/graphs/_graph.py
pywgraph/graphs/_paths.py
pywgraph/groups/__init__.py
pywgraph/groups/_groups.py
pywgraph/groups/_predefined_groups.py
tests/__init__.py
tests/test_directed_edge.py
tests/test_path_finding.py
tests/test_path_finding_new.py
tests/test_paths_and_cycles.py
tests/test_weighted_directed_edge.py
tests/test_weighted_directed_graph.py
tests/test_weighted_directed_graph_arrays.py
pywgraph-1.1.0.dist-info/METADATA
pywgraph-1.1.0.dist-info/WHEEL
pywgraph-1.1.0.dist-info/top_level.txt
pywgraph-1.1.0.dist-info/RECORD
