Metadata-Version: 2.1
Name: pywgraph
Version: 1.1.0
Summary: A python implementation of weighted directed graphs
Home-page: https://github.com/josek98/pywgraph
Author: josek98
Author-email: josemmsscc98@gmail.com
Requires-Python: >=3.10
Provides-Extra: dev
Requires-Dist: pytest >=7.0 ; extra == 'dev'
Requires-Dist: twine >=4.0.2 ; extra == 'dev'
